{"14617":["Rochester"],"161":["Moose Jaw"],"8E 0X5":["Whistler"],"B3B 1W8":["Dartmouth"],"B5A 1B6":["Yarmouth"],"B5A 1J9":["Yarmouth"],"B5A 2T6":["Yarmouth"],"B5A 3H6":["Yarmouth"],"B5A 4B1":["Yarmouth"],"B5A 5Z7":["Hebron"],"B9A 1M5":["Port Hawkesbury"],"BC V1Y 6H2":["Kelowna"],"E2K 4K9":["Saint John"],"E2K 4L1":["Saint John"],"E2K 4M5":["Saint John"],"E2K 5T6":["Saint John"],"E2K 5T7":["Saint John"],"E9E 2H9":["Doyles Brook"],"G0A 4N0":["Shannon"],"G0C 2A0":["Newport"],"G0E 1W0":["Murdochville"],"G0L 1J0":["Pohénégamook"],"G0R 1H0":["Cap-Saint-Ignace"],"G1K 2Z8":["Québec"],"G1K 3G4":["Québec"],"G1K 8L8":["Québec"],"G1R 1R6":["Québec"],"G1R 1R8":["Québec"],"G1R 2M7":["Québec"],"G1R 3Y9":["Québec"],"G1R 4B9":["Québec"],"G1R 4C7":["Québec"],"G1R 4H8":["Quebec"],"G1W 0E8":["Québec"],"G1W 1L8":["Québec"],"G3C 0K7":["Stoneham-et-Tewkesbury"],"G3C 1T3":["Stoneham-et-Tewkesbury"],"G7H 1T5":["Chicoutimi"],"G7H 4C1":["Chicoutimi"],"G7H 4C3":["Chicoutimi"],"G7H 5N6":["Chicoutimi"],"G7H 5S5":["Chicoutimi"],"G8B 5W1":["Alma"],"H1V 3A6":["Montréal"],"H1Z 3E3":["Montréal"],"H2J 1X2":["Montréal"],"H2L 2H2":["Montréal"],"H2L 2H4":["Montréal"],"H2L 3L6":["Montréal"],"H2L 3T1":["Montréal"],"H2L 3Z3":["Montréal"],"H2L 4P5":["Montréal"],"H2M 1S3":["Montréal"],"H2M 2E5":["Montréal"],"H2M 2M2":["Montréal"],"H2N 1M4":["Montréal"],"H2R 1G4":["Montréal"],"H2R 2X9":["Montreal"],"H2T 1P8":["Montréal"],"H2V 1K5":["Montreal"],"H2X":["Montreal"],"H2X 1K3":["Montréal"],"H2Y 1G8":["Montréal"],"H2Y 1V9":["Montréal"],"H2Z 1J6":["Montréal"],"H3A 1B4":["Montreal"],"H3A 3G4":["Montréal"],"H3A 4W5":["Montreal"],"H3B 4G1":["Montreal"],"H3B 4G7":["Montréal"],"H3E 1T8":["Verdun"],"H3G 2H1":["Montréal"],"H3G 2H6":["Montréal"],"H3H 1N2":["Montreal"],"H3S 2J3":["Montréal"],"H3T 1X8":["Montréal"],"H3T 1Y1":["Montréal"],"H3T 2B1":["Montreal"],"H3X 1V1":["Montréal;Montreal"],"H3X 1V4":["Montréal;Montreal"],"H4A 1T9":["Montréal"],"H4C 1R1":["Montreal"],"H4C 2S6":["Montréal"],"H4L 2A1":["Saint-Laurent"],"H4P 2T5":["Montréal"],"H4R 1Y8":["Saint-Laurent"],"H4Y 1H1":["Dorval"],"H9B 1Z6":["Dollard-Des Ormeaux"],"J3V 2K4":["Saint-Bruno-de-Montarville"],"J4K 2V1":["Longueuil"],"J8E 1K4":["Mont-Tremblant"],"J8N 7T5":["Val-des-Monts"],"K0E 1R0":["Mallorytown"],"K0K 1G0":["Bloomfield"],"K0K 1T0":["Consecon"],"K0K 2T0":["Picton","Prince Edward"],"K0K 3L0":["Wellington"],"K6V 2H6":["Brockville"],"K6V 3R8":["Brockville"],"K6V 4W4":["Brockville"],"K6V 5T3":["Brockville"],"K9A 0G1":["Cobourg"],"K9A 0H6":["Cobourg"],"K9A 1K6":["Cobourg"],"K9A 2L2":["Cobourg"],"K9A 2M4":["Cobourg"],"K9A 3A5":["Cobourg"],"K9A 3A7":["Cobourg"],"K9A 3S1":["Cobourg"],"K9A 4J9":["Cobourg"],"L0G 1W0":["Tottenham"],"L0N 1S3":["Shelburne"],"L0R 2H0":["Waterdown"],"L1A 0E2":["Port Hope"],"L1A 2S7":["Port Hope"],"L1A 2Z2":["Port Hope"],"L1A 3V7":["Port Hope"],"L1C 3L4":["Bowmanville"],"L1E 2J6":["Courtice"],"L1G 1C7":["Oshawa"],"L1G 4R8":["Oshawa"],"L1G 4S2":["Oshawa"],"L1G 4X3":["Oshawa"],"L1P 1P7":["Whitby"],"L1R 2G7":["Whitby"],"L1W 3V4":["pickering"],"L3P 1B8":["Markham"],"L3R 0B5":["Markham"],"L3R 4X9":["Markham"],"L3T 5W6":["Markham"],"L4C 5G2":["Richmond Hill"],"L4G 1W3":["Aurora"],"L4H 0R2":["Woodbridge"],"L4J 6W7":["Thornhill"],"L4J 7Y3":["Thornhill"],"L4J 8G7":["Thornhill"],"L4K 1A2":["Vaughan"],"L4K 3G1":["Vaughan"],"L4L 8L5":["Woodbridge"],"L4M 0J7":["Barrie"],"L4S 0B2":["Richmond Hill"],"L5B 0A1":["Mississauga"],"L5J 2Y4":["Mississauga"],"L5N 6A3":["Mississauga"],"L5S 1Z2":["Mississauga"],"L5V 2X8":["Mississauga"],"L5V 2Y1":["Mississauga"],"L6H 6Y3":["Oakville"],"L6H 7S8":["Oakville"],"L6J 1H3":["Oakville"],"L6J 4A8":["Oakville"],"L6J 7S2":["Oakville"],"L6K 0H9":["Oakville"],"L6K 2E2":["Oakville"],"L6K 2G4":["Oakville"],"L6K 3A4":["Oakville"],"L6K 3B3":["Oakville"],"L6K 3S4":["Oakville"],"L6K 3W8":["Oakville"],"L6L 0B6":["Oakville"],"L6L 1H2":["Oakville"],"L6L 3B6":["Oakville"],"L6L 3B7":["Oakville"],"L6L 3B8":["Oakville"],"L6M 1M1":["Oakville"],"L6M 2R7":["Oakville"],"L6T 5P1":["Brampton"],"L7C 1M6":["Caledon"],"L7K 1W8":["Caledon"],"L7L 0A2":["Burlington"],"L7L 0B6":["Burlington"],"L7L 2A4":["Burlington"],"L7M 0V6":["Burlington"],"L7R 1A2":["Burlington"],"L7R 2G3":["Burlington"],"L7R 2G4":["Burlington"],"L7R 2N1":["Burlington"],"L7R 2N2":["Burlington"],"L7R 2Y4":["Burlington"],"L7R 3Z6":["Burlington"],"L7S 1W6":["Burlington"],"L8E 3L8":["Hamilton"],"L8S 1G5":["Hamilton"],"L9L 1A3":["Port Perry"],"L9R 0A6":["Alliston"],"L9R 1B5":["Alliston"],"L9R 1E8":["Alliston"],"L9R 1G8":["Alliston"],"L9R 1J3":["Alliston"],"L9R 1K4":["Alliston"],"L9R 1L7":["Alliston"],"L9R 1P8":["Alliston"],"L9R 1R2":["Alliston"],"L9R 1T4":["Alliston"],"L9R 1T7":["Alliston"],"L9T 0J4":["Milton"],"L9V 0N8":["Shelburne"],"L9V 1B6":["Mono"],"L9V 3K7":["Shelburne"],"L9W 1K2":["Orangeville"],"L9W 1K4":["Orangeville"],"L9W 1R4":["Orangeville"],"L9W 2M2":["Orangeville"],"L9W 2M3":["Orangeville"],"L9W 3N8":["Orangeville"],"L9W 3Y3":["Orangeville"],"L9W 4W8":["Orangeville"],"L9W 4X9":["Orangeville"],"L9W 5G4":["Orangeville"],"L9W 5L1":["Orangeville"],"L9W 6W6":["Orangeville"],"M1L 2L9":["Scarborough"],"M1S 3P6":["Scarborough"],"M2N 5V7":["North York"],"M3B 1Y2":["North York"],"M3J 0G9":["North York"],"M3J 1N6":["North York"],"M3J 2A7":["North York"],"M3J 2B1":["North York"],"M3J 2C6":["North York"],"M3J 2G5":["Toronto"],"M3J 2J1":["North York"],"M3J 2K1":["North York"],"M3J 2M4":["North York"],"M3J 2N7":["North York"],"M3J 2P7":["North York"],"M3J 2R8":["North York"],"M3J 2T2":["North York"],"M3J 2T8":["North York"],"M3J 2W6":["North York"],"M3J 3A7":["North York"],"M3J 3J4":["Toronto"],"M3J 3K2":["North York"],"M3J 3N2":["North York"],"M3J 3N3":["North York"],"M3J 3T8":["North York"],"M3K 2A2":["North York"],"M3K 3E5":["North York"],"M4E 1E3":["Toronto"],"M4L 1J3":["Toronto"],"M4N 1A5":["Picton"],"M4P 2H7":["Toronto"],"M4S 1Z8":["Toronto"],"M5J 1T1":["Toronto"],"M6B 3S8":["North York"],"M6E 2J3":["York"],"M6E 2J5":["York"],"M6E 2K3":["York"],"M6G 2N3":["Toronto"],"M9M 2Y9":["Toronto"],"M9V 2X5":["Etobicoke"],"N0B 2N0":["St Jacobs","St. Jacobs"],"N0E 1W0":["Vittoria"],"N0R 1J0":["Amherstburg"],"N1E 3J3":["Guelph"],"N1E 5G6":["Guelph"],"N1G 4T7":["Guelph"],"N1H 0B4":["Guelph"],"N1H 1B1":["Guelph"],"N1H 1G7":["Guelph"],"N1H 2T1":["Guelph"],"N1H 2Y6":["Guelph"],"N1H 2Z7":["Guelph"],"N1H 3A1":["Guelph"],"N1H 3A2":["Guelph"],"N1H 3V4":["Guelph"],"N1H 3Z1":["Guelph"],"N1H 4E3":["Guelph"],"N1H 4E9":["Guelph"],"N1H 5W4":["Guelph"],"N1H 6H7":["Guelph"],"N1H 6H8":["Guelph"],"N1H 7T8":["Guelph"],"N1H 7Z9":["Guelph"],"N1K 1S5":["Guelph"],"N1L 0M6":["Guelph"],"N1L 1C9":["Guelph"],"N1R 6X7":["Cambridge"],"N2E 4B3":["Kitchener"],"N2G 1A6":["Kitchener"],"N2G 1B7":["Kitchener"],"N2G 1B9":["Kitchener"],"N2G 4P3":["Kitchener"],"N2G 4X8":["Kitchener"],"N2H 2G8":["Kitchener"],"N2H 4Y5":["Kitchener"],"N2J 2X3":["Waterloo"],"N2J 3G9":["Waterloo"],"N2J 4G8":["Waterloo"],"N2K 0B3":["Waterloo"],"N2L 4G8":["Waterloo"],"N2L 4M3":["Waterloo"],"N2L 6A1":["Waterloo"],"N2M 3C2":["Kitchener"],"N2N 0B1":["Kitchener"],"N2P 3W6":["Kitchener"],"N2V 1B4":["Waterloo"],"N2V 1K7":["Waterloo"],"N2V 2A1":["Waterloo"],"N2V 2J9":["Waterloo"],"N3B 2P5":["Elmira"],"N8N 1W1":["Tecumseh"],"N8N 2M1":["Windsor"],"N8R 1A8":["Windsor"],"N8T 1B6":["Windsor"],"N8W 1C1":["Windsor"],"N8W 5M5":["Windsor"],"N8X 4W2":["Windsor"],"N8Y 1Z6":["Windsor"],"N8Y 2P8":["Windsor"],"N8Y 4K9":["Windsor"],"N9A 4L2":["Windsor"],"N9B 1K3":["Windsor"],"N9G 1S7":["Windsor"],"N9H 1S3":["Windsor"],"N9H 1S4":["Lasalle"],"R0H 0L0":["Kinosota"],"R0J 0X0":["Inglis"],"R2M 3C8":["Winnipeg"],"R2M 3V7":["Winnipeg"],"R2M 3W4":["winnipeg","Winnipeg"],"R2M 4Z2":["Winnipeg"],"R2M 5L6":["Winnipeg"],"R2M 5M3":["Winnipeg"],"R2N 0A5":["Winnipeg"],"R3B 2A9":["Winnipeg"],"R3C 3J1":["Winnipeg"],"R3G 0V2":["Winnipeg"],"R3M 2A6":["Winnipeg"],"R3N 1T8":["Winnipeg"],"R3N 1Z2":["Winnipeg"],"R3P 0N3":["Winnipeg"],"R3P 0Y4":["Winnipeg"],"R3P 1E9":["Winnipeg"],"R3T 5C2":["Winnipeg"],"R3T 5L1":["Winnipeg"],"R3X 0N3":["Winnipeg"],"R3Y 0A1":["Winnipeg"],"R3Y 1V5":["Winnipeg"],"R7A 5B3":["Brandon"],"R7N 1C2":["Dauphin"],"R7N 1G9":["Dauphin"],"R7N 1K3":["Dauphin"],"R7N1C2":["Dauphin"],"S0G 0E0":["Balgonie"],"S0K 2T0":["Martensville"],"S0K 4S1":["Warman"],"S4M 0A1":["Regina"],"S4N 0N3":["Regina"],"S4N 0V6":["Regina"],"S4N 6T5":["Regina"],"S4P 0J5":["regina","Regina"],"S4P 0P8":["Regina"],"S4P 0R3":["Regina"],"S4P 2B8":["Regina"],"S4P 2G9":["Regina"],"S4P 2L3":["Regina"],"S4P 3C8":["Regina"],"S4P 3X1":["Regina"],"S4P 3Y6":["Regina"],"S4R 1E9":["Regina"],"S4R 1H5":["Regina"],"S4R 1W4":["Regina"],"S4R 1W6":["Regina"],"S4R 1Z8":["Regina"],"S4R 2B6":["Regina"],"S4R 4M7":["Regina"],"S4T 1N3":["Regina"],"S4V 2Z3":["Regina"],"S4V 3A3":["Regina"],"S4V 3T7":["Regina"],"S4W 0B7":["Regina"],"S4W 1B7":["Regina"],"S4X 4J7":["Regina"],"S6H 0A1":["Moose Jaw"],"S6H 0B7":["Moose Jaw"],"S6H 0W1":["Moose Jaw"],"S6H 0W2":["Moose Jaw"],"S6H 1R1":["Moose Jaw"],"S6H 1S4":["Moose Jaw"],"S6H 1W8":["Moose Jaw"],"S6H 2B5":["Moose Jaw"],"S6H 3J6":["Moose Jaw"],"S6H 3J8":["Moose Jaw"],"S6H 3J9":["Moose Jaw"],"S6H 3L9":["Moose Jaw"],"S6H 4P2":["Moose Jaw"],"S6H 4X6":["Moose Jaw"],"S6H 5V3":["Moose Jaw"],"S6H 6L7":["Moose Jaw"],"S6H 6M3":["Moose Jaw"],"S6J 0A5":["Moose Jaw"],"S6J 0A9":["Moose Jaw"],"S7H 0S5":["Saskatoon"],"S7H 0T8":["Saskatoon"],"S7H 0W5":["Saskatoon"],"S7K 0J5":["Saskatoon"],"S7K 0M5":["Saskatoon"],"S7K 1K5":["Saskatoon"],"S7K 1M6":["Saskatoon"],"S7K 2E1":["Saskatoon"],"S7K 4Z6":["Saskatoon"],"S7L 0V2":["Saskatoon"],"S7L 5X5":["Saskatoon"],"S7L 6M4":["Saskatoon"],"S7L6B7":["Saskatoon"],"S7M 1M6":["Saskatoon"],"S7M 2A2":["Saskatoon"],"S7R 0M8":["Saskatoon"],"S7S 0A5":["Saskatoon"],"S7T 0G3":["Saskatoon"],"S7T 0V1":["Saskatoon"],"T0C 1Z0":["Leduc County"],"T0J 0Y7":["Drumheller"],"T0L 0A0":["Aldersyde"],"T1B 0E3":["Medicine Hat"],"T1B 2R4":["Medicine Hat"],"T1H 5C9":["Lethbridge"],"T1H 6G2":["Lethbridge"],"T1J 0E3":["Lethbridge"],"T1J 1W4":["Lethbridge"],"T1J 2C7":["Lethbridge"],"T1J 2M7":["Lethbridge"],"T1J 4H1":["Lethbridge"],"T1J 4T3":["Lethbridge"],"T1J 5B3":["Lethbridge"],"T1K 1A2":["Lethbridge"],"T1K 2R5":["Lethbridge"],"T1S 0B2":["Okotoks"],"T1S 0N8":["Okotoks"],"T1S 1A9":["Okotoks"],"T1S 1B1":["Okotoks"],"T1S 1J7":["Okotoks"],"T1S 1J9":["Okotoks"],"T1S 1K1":["Okotoks"],"T1S 1L2":["Okotoks"],"T1S 1M3":["Okotoks"],"T1S 2E1":["Okotoks"],"T1S 2E7":["Okotoks"],"T1V 1G3":["High River"],"T1W 0R3":["Calgary"],"T1W 1P4":["Canmore"],"T1W 1S2":["Canmore"],"T1W 2A7":["Canmore"],"T1W 2B2":["Canmore"],"T1W 2B3":["Canmore"],"T1W 2B6":["Canmore"],"T1W 2G9":["Canmore"],"T1Y 5N4":["Calgary"],"T1Y 6R3":["Calgary"],"T2A 5Z7":["Calgary"],"T2A 6K3":["Calgary"],"T2A 7A7":["Calgary"],"T2C 1K2":["Calgary"],"T2C 2R9":["Calgary"],"T2C 5E1":["Calgary"],"T2E 1J9":["Calgary"],"T2E 4P9":["calgary"],"T2E 6Y4":["Calgary"],"T2E 6Z3":["Calgary"],"T2E 7V6":["Calgary"],"T2G 0K6":["Calgary"],"T2G 0T5":["Calgary"],"T2G 1H3":["Calgary"],"T2G 1X4":["Calgary"],"T2G 1Y3":["Calgary"],"T2G 3G3":["Calgary"],"T2G 3Z8":["Calgary"],"T2G 4T9":["Calgary"],"T2G 4X4":["Calgary"],"T2G 5E1":["Calgary"],"T2G 5T4":["Calgary"],"T2H 0H9":["Calgary"],"T2H 0L8":["Calgary"],"T2H 0W4":["Calgary"],"T2H 0Y8":["Calgary"],"T2H 0Y9":["Calgary"],"T2H 1C3":["Calgary"],"T2H 3B8":["Calgary"],"T2J 6A9":["Calgary"],"T2M 0K9":["Calgary"],"T2M 4N5":["Calgary"],"T2N 3P4":["Calgary"],"T2N 4T3":["Calgary"],"T2P 0K4":["Calgary"],"T2P 1J9":["Calgary"],"T2P 2M5":["Calgary"],"T2S 0A5":["Calgary"],"T2S 1G9":["Calgary"],"T2T 0A7":["Calgary"],"T2T 4M2":["Calgary"],"T2T 5R6":["Calgary"],"T2T 6T7":["Calgary"],"T2V 1R1":["Calgary"],"T2W 0K3":["Calgary"],"T2W 4Y1":["Calgary"],"T2Y 3H9":["Calgary"],"T2Z 0G4":["Calgary"],"T3B 5R5":["Calgary"],"T3B 6B7":["Calgary"],"T3C 0M5":["Calgary"],"T3E 6W9":["Calgary"],"T3G 4J8":["Calgary"],"T3H 1S6":["Calgary"],"T3H 3P8":["Calgary"],"T3H 4E5":["Calgary"],"T3J 5H3":["Calgary"],"T3K 0B3":["Calgary"],"T3M 0A4":["Calgary"],"T3M 0T2":["Calgary"],"T3M 1T4":["Calgary"],"T3M 2P8":["Calgary"],"T3M 2T5":["Calgary"],"T3N 1A8":["Calgary"],"T3R 0A1":["Calgary"],"T3R 0R5":["Calgary"],"T3Z 2E9":["Calgary"],"T4A 0C4":["Airdrie"],"T4A 0E1":["Airdrie"],"T4A 0H6":["Airdrie"],"T4A 0V4":["Airdrie"],"T4B 0P7":["Airdrie"],"T4B 0R3":["Airdrie"],"T4B 0R6":["Airdrie"],"T4B 0S9":["Airdrie"],"T4B 1R9":["Airdrie"],"T4B 1S2":["Airdrie"],"T4B 2N1":["Airdrie"],"T4B 2N2":["Airdrie"],"T4B 2Y5":["Airdrie"],"T4B 3C3":["Airdrie"],"T4B 3K3":["Airdrie"],"T4B 4J3":["Airdrie"],"T4C 2N1":["Cochrane"],"T4E 1B2":["Red Deer"],"T4P 0M9":["Red Deer"],"T4P 0N1":["Red Deer"],"T4S 0B6":["Sylvan Lake"],"T4V 1P6":["Camrose"],"T4V 1P9":["Camrose"],"T4V 1R1":["Camrose"],"T4V 2R3":["Camrose"],"T4V 2Y8":["Camrose"],"T4V 2Z1":["Camrose"],"T4V 4R1":["Camrose"],"T4V 4S3":["Camrose"],"T4X 2S4":["Leduc County"],"T7X 0C8":["Spruce Grove"],"T7X 0G2":["Spruce Grove"],"T7X 0G6":["Spruce Grove"],"T7X 0J6":["Spruce Grove"],"T7X 2C6":["Spruce Grove"],"T7X 2K5":["Spruce Grove"],"T7X 2Z7":["Spruce Grove"],"T7X 3A2":["Spruce Grove"],"T7X 3A3":["Spruce Grove"],"T7X 3A9":["Spruce Grove"],"T7X 3B3":["Spruce Grove"],"T7X 3B5":["Spruce Grove"],"T7X 3X2":["Spruce Grove"],"T7X 3Y1":["Spruce Grove"],"T7X 4A3":["Spruce Grove"],"T7X 4B8":["Spruce Grove"],"T7X 4J3":["Spruce Grove"],"T7X 4P9":["Spruce Grove"],"T7Y 2N4":["Parkland County"],"T7Z 0B1":["Stony Plain"],"T7Z 0G6":["Stony Plain"],"T7Z 0H6":["Stony Plain"],"T7Z 0K3":["Stony Plain"],"T7Z 1G2":["Stony Plain"],"T7Z 1N3":["Stony Plain"],"T7Z 1P8":["Stony Plain"],"T7Z 1T2":["Stony Plain"],"T7Z 1T3":["Stony Plain"],"T7Z 1T4":["Stony Plain"],"T7Z 1T5":["Stony Plain"],"T7Z 1V6":["Stony Plain"],"T7Z 1X7":["Stony Plain"],"T8A 2G4":["Sherwood Park"],"T8A 4N5":["Sherwood Park"],"T8A 5P7":["Sherwood Park"],"T8B 1B8":["Sherwood Park"],"T8B 1M6":["Sherwood Park"],"T8H 0N6":["Sherwood Park"],"T8H 0P1":["Sherwood Park"],"T8H 0P5":["Sherwood Park"],"T8H 0Z9":["sherwood Park"],"T8H 1R4":["Sherwood Park"],"T8H 1S5":["Sherwood Park"],"T8H 1S8":["Sherwood Park"],"T8L 0B2":["Fort Saskatchewan"],"T8L 0C5":["Fort Saskatchewan"],"T8N 3X4":["St. Albert"],"T8N 3Z9":["St. Albert"],"T8N 4J8":["St. Albert"],"T8N 6L5":["St. Albert"],"T8N 7V2":["St. Albert"],"T8V 7Y5":["Grande Prairie"],"T8V 8J6":["Grande Prairie"],"T8W 0G9":["Grande Prairie"],"T9A 1V5":["Wetaskiwin"],"T9E 4C4":["Leduc"],"T9E 6K8":["Leduc"],"T9E 6T2":["Leduc"],"T9E 6T4":["Leduc"],"T9E 6V9":["Leduc"],"T9E 6X9":["Leduc"],"T9E 6Z6":["Leduc"],"T9E 7A5":["Leduc"],"T9E 7B3":["Leduc"],"T9E 7K2":["Leduc"],"T9E 7K9":["Leduc"],"T9E 7L1":["Leduc"],"T9E 7Y9":["Nisku"],"T9E 8L9":["Leduc"],"T9H 0J5":["Fort McMurray"],"T9H 1L2":["Fort McMurray"],"T9H 1W5":["Fort McMurray"],"T9H 2J3":["Fort McMurray"],"T9H 2K4":["Fort McMurray"],"T9H 3E1":["Fort McMurray"],"T9H 4A4":["Fort McMurray"],"T9H 5G2":["Fort McMurray"],"T9K 1P1":["Fort McMurray"],"T9K 1S6":["Fort McMurray"],"T9K 2L9":["Fort McMurray"],"T9V 0X9":["Lloydminster"],"V0H 1Z8":["Summerland"],"V0N 1B0":["Whistler"],"V0N 1B1":["Whistler"],"V0N 1B4":["Whistler"],"V0N 1B7":["Whistler"],"V0N 1B9":["Whistler"],"V0N 1H0":["Brackendale"],"V0N 1T0":["Squamish"],"V0N1B4":["Whistler"],"V0N1T0":["Squamish"],"V0R 1L4":["Cobble Hill"],"V0R 1L5":["Cobble Hill"],"V0R 1M0":["Coombs"],"V0R 1N0":["Cowichan Bay"],"V0R 1R0":["crofton"],"V0R 2P0":["Mill Bay"],"V0R 2P1":["Mill Bay"],"V0R 2W3":["Shawnigan Lake"],"V0R 6L8":["Duncan"],"V0R1L0":["Area C (Cobble Hill)"],"V1B 2L4":["Coldstream"],"V1B 2L9":["Coldstream"],"V1B 2N5":["Coldstream"],"V1B 3C7":["Coldstream"],"V1J 0E9":["Fort St John"],"V1J 6V5":["Fort St John"],"V1M 0A4":["Langley"],"V1M 0B3":["Langley"],"V1T 2C1":["Vernon"],"V1T 5N4":["Vernon"],"V1T 5P3":["Vernon"],"V1T 7E3":["Vernon"],"V1T 7M3":["Vernon"],"V1T 8X2":["Vernon"],"V1T 9G8":["Vernon"],"V1T 9H2":["Vernon"],"V1V 1Y1":["Kelowna"],"V1V 2Y4":["Kelowna"],"V1V 3C8":["Kelowna"],"V1V 3E9":["Kelowna"],"V1W 2E1":["Kelowna"],"V1W 3E9":["Kelowna"],"V1W 4M7":["Kelowna"],"V1W 4V5":["Kelowna"],"V1X 4H9":["Kelowna"],"V1X 7V7":["Kelowna"],"V1X 7Y5":["Kelowna"],"V1Y 1A9":["Kelowna"],"V1Y 1J4":["Kelowna"],"V1Y 1P4":["Kelowna"],"V1Y 1W2":["Kelowna"],"V1Y 1Z9":["Kelowna"],"V1Y 4R2":["Kelowna"],"V1Y 4Y8":["Kelowna"],"V1Y 6E8":["Kelowna"],"V1Y 6H2":["Kelowna","kelowna"],"V1Y 6L2":["Kelowna"],"V1Y 6L3":["Kelowna"],"V1Y 6N2":["Kelowna"],"V1Y 6S4":["Kelowna"],"V1Y 6S7":["Kelowna"],"V1Y 7E4":["Kelowna"],"V1Y 8J8":["Kelowna"],"V1Y 9V1":["Kelowna"],"V1Y 9V8":["Kelowna"],"V1Y 9Z7":["Kelowna"],"V1Y6N2":["Kelowna"],"V2A 6W6":["Penticton"],"V2B 3H9":["Kamloops"],"V2B 7Z2":["Kamloops"],"V2C 1A6":["Kamloops"],"V2C 4N6":["Kamloops"],"V2C 5J1":["Kamloops"],"V2C 6M1":["Kamloops"],"V2C 6R6":["Kamloops"],"V2C 6T6":["Kamloops"],"V2H 1P6":["Kamloops"],"V2K 1Z8":["Prince George"],"V2L 2P4":["Prince George"],"V2L 3E8":["Prince George"],"V2L 3G7":["Prince George"],"V2L 3L5":["Prince George"],"V2L 4V7":["Prince George"],"V2L 5L1":["Prince George"],"V2L 5R5":["Prince George"],"V2M 1T1":["Prince George"],"V2M 3C6":["Prince George"],"V2N 0B2":["Prince George"],"V2N 0E1":["Prince George"],"V2N 0G2":["Prince George"],"V2N 1V9":["Prince George"],"V2N 2S9":["Prince George"],"V2N 4Z9":["Prince George"],"V2N 5N7":["Prince George"],"V2N 7A3":["Prince George"],"V2P 1B5":["Chilliwack"],"V2P 2M3":["Chilliwack"],"V2P 3J3":["Chilliwack"],"V2P 3Z8":["Chilliwack"],"V2P 4N2":["Chilliwack"],"V2P 6H3":["Chillwack"],"V2P 6Z3":["Chilliwack"],"V2P 7N1":["Chiliwack"],"V2R 0P9":["Chilliwack"],"V2R 1A1":["Chilliwack"],"V2R 3Z8":["Chilliwack"],"V2R 4A7":["Chilliwack"],"V2R 4G6":["Chilliwack"],"V2R 5P9":["chilliwack"],"V2R 5Z5":["Chilliwack"],"V2T 4V1":["Abbotsford"],"V2T 4W1":["Abbotsford"],"V2X 2P9":["Maple Ridge"],"V2Y 1K9":["Langley"],"V2Z 1E3":["Langley"],"V3A 3Y9":["Langley"],"V3A 4G3":["Langley"],"V3A 4G8":["City of Langley"],"V3B 0G9":["Port Coquitlam"],"V3G 1E1":["Abbotsford"],"V3L 3B9":["New Westminster"],"V3N 3L4":["Burnaby"],"V3S 1G0":["Surrey"],"V3S 2L5":["Surrey"],"V3S 2X6":["Surrey"],"V3S 7Y3":["Surrey"],"V3S 9A5":["Surrey"],"V3T 1V8":["Surrey"],"V3W 3A6":["Surrey"],"V3W 5B4":["Surrey"],"V3Z 0Z5":["Surrey"],"V4A 2H9":["Surrey"],"V4A 4N7":["Surrey"],"V4C 0C1":["Delta"],"V4C 6P5":["Delta"],"V4K 1W4":["Delta"],"V4L 2A4":["Delta"],"V4P 1H5":["Surrey"],"V4P0E5":["Surrey"],"V4T 2E4":["West Kelowna"],"V4T 2J3":["West Kelowna"],"V4T 3E3":["Westbank"],"V4V 1G5":["Lake Country"],"V4V 1J6":["Lake Country"],"V4V 1K1":["Lake Country"],"V5B 2J8":["Burnaby"],"V5C 2H5":["Burnaby"],"V5C 2J3":["Burnaby"],"V5C 2J6":["Burnaby"],"V5E 3N1":["Burnaby"],"V5G 3T7":["Burnaby"],"V5G 4A3":["Burnaby"],"V5H 0E5":["Burnaby"],"V5J 0A3":["Burnaby"],"V5M 4N9":["Vancouver"],"V5N 4A9":["Vancouver"],"V5T 3G1":["Vancouver"],"V5V 1N9":["Vancouver"],"V6B 2B3":["Vancouver"],"V6G 1P5":["Vancouver"],"V6G 2M3":["Vancouver"],"V6H 3K1":["Vancouver"],"V6J 3B1":["Vancouver"],"V7T 2Z3":["West Vancouver"],"V8B 0A0":["Squamish"],"V8B 0A3":["Squamish"],"V8B 0A8":["Squamish"],"V8B 0C3":["Squamish"],"V8B 0C4":["Squamish"],"V8B 0G2":["Squamish"],"V8B 0G5":["Squamish"],"V8B 0H1":["Squamish"],"V8B 0R5":["Squamish"],"V8B 0S8":["Squamish"],"V8B 0V2":["Squamish"],"V8B 1A0":["Squamish"],"V8E 0W5":["Whistler"],"V8E 0X5":["Whistler"],"V8E 0X9":["Whistler"],"V8E 0Y2":["Whistler"],"V8E 1B4":["Whistler"],"V8E 1B6":["Whistler"],"V8E 1G7":["Whistler"],"V8E 1G9":["Whistler"],"V8E 1H8":["Whistler"],"V8E 1M2":["Whistler"],"V8E 1M3":["Whistler"],"V8E0B6":["Whistler"],"V8E0G1":["Whistler"],"V8G 2X8":["Terrace"],"V8J 1H1":["Prince Rupert"],"V8J 1K7":["Prince Rupert"],"V8J 1L2":["Prince Rupert"],"V8J 1L3":["Prince Rupert"],"V8J 1L7":["Prince Rupert"],"V8J 1M8":["Prince Rupert"],"V8J 1M9":["Prince Rupert"],"V8J 3S5":["Prince Rupert"],"V8J 3X4":["Prince Rupert"],"V8T 2C5":["Victoria"],"V9B 0J8":["Colwood"],"V9B 0J9":["Victoria"],"V9B 2A6":["Victoria"],"V9B 2X4":["Langford","Victoria"],"V9B 2X8":["Langford"],"V9B 3R4":["Langford"],"V9B 3R5":["Victoria"],"V9L 1M8":["Duncan"],"V9L 1N5":["Duncan"],"V9L 1N8":["Duncan"],"V9L 1V2":["Duncan"],"V9L 3R6":["Duncan"],"V9L 5J2":["Duncan"],"V9L 5W9":["Duncan"],"V9L 6E1":["Duncan"],"V9L 6J7":["Duncan"],"V9L 6M3":["Duncan"],"V9L 6W3":["Duncan"],"V9R 3A7":["Nanaimo"],"V9R 5B2":["Nanaimo"],"V9R 5E7":["Nanaimo"],"V9R 5G4":["Nanaimo"],"V9R 5G5":["Nanaimo"],"V9R 5G6":["Nanaimo"],"V9T 1W1":["Nanaimo"],"V9T 2L8":["Nanaimo"],"V9T 2L9":["Nanaimo"],"V9T 4C8":["Nanaimo"],"V9T 6L8":["Nanaimo"],"V9X 1J4":["Nanaimo"],"v6k2H5":["Vancouver"]}