{"104 47":["Αθήνα"],"10431":["Αθήνα"],"10432":["Αθήνα"],"10433":["Αθήνα"],"10434":["Αθήνα"],"10436":["Αθήνα"],"10437":["Athens","Αθήνα"],"10438":["Αθήνα"],"10439":["Αθήνα"],"10440":["Αθήνα"],"10442":["Αθήνα"],"10443":["Αθήνα"],"10444":["Αθήνα"],"10445":["Αθήνα"],"10446":["Αθήνα"],"105 56":["Αθήνα"],"105 63":["Αθήνα"],"10551":["Αθήνα"],"10552":["Αθήνα"],"10553":["Αθήνα"],"10554":["Αθήνα"],"10555":["Αθήνα"],"10556":["Αθήνα"],"10557":["Αθήνα"],"10558":["Αθήνα"],"10559":["Αθήνα"],"10560":["Αθήνα"],"10561":["Αθήνα"],"10562":["Αθήνα"],"10563":["Αθήνα"],"10564":["Αθήνα"],"10671":["Αθήνα"],"10674":["Αθήνα","Athene"],"10675":["Αθήνα"],"10676":["Αθήνα"],"10677":["Αθήνα"],"10678":["Αθήνα","Αθηνα"],"10679":["Αθήνα"],"10680":["Αθήνα"],"10681":["Αθήνα"],"10682":["Αθήνα"],"10683":["Αθήνα"],"11143":["Αθήνα"],"11144":["Αθήνα"],"11145":["Αθήνα"],"11146":["Γαλάτσι"],"11251":["Αθήνα"],"11252":["Αθήνα"],"11253":["Αθήνα"],"11257":["Αθήνα"],"11361":["Αθήνα"],"11362":["Αθήνα"],"11363":["Αθήνα"],"11471":["Αθήνα"],"11471;11472":["Αθήνα"],"11472":["Αθήνα"],"11473":["Αθήνα"],"11474":["Αθήνα"],"11476":["Αθήνα"],"11521":["Αθήνα"],"11522":["Αθήνα"],"11524":["Αθήνα"],"11525":["Αθήνα"],"11527":["Αθήνα"],"11528":["Αθήνα"],"11632":["Αθήνα"],"11635":["Αθήνα"],"11742":["Αθήνα"],"11743":["Αθήνα"],"11744":["Αθήνα"],"11852":["Αθήνα"],"11853":["Αθήνα"],"11854":["Αθήνα"],"12132":["Περιστέρι"],"12135":["Περιστέρι"],"12136":["Περιστέρι"],"122 44":["Aιγαλεω"],"12243":["Αιγάλεω"],"12244":["Αιγάλεω"],"12461":["Χαϊδάρι"],"13123":["Ίλιον"],"13231":["Πετρούπολη"],"13671":["Αχαρναί"],"13672":["Αχαρνές"],"13677":["Αχαρνές"],"142 31":["Νέα Ιωνία"],"14231":["Νέα Ιωνία"],"14233":["Νέα Ιωνία"],"14451":["Μεταμόρφωση"],"14564":["Κηφισιά"],"151 27":["Μελίσσια"],"15124":["Μαρούσι"],"15233":["Χαλάνδρι"],"15234":["Χαλάνδρι"],"15235":["Βριλήσσια"],"15342":["Αθήνα"],"15451":["Ψυχικό"],"15710":["Ζωγράφου"],"15771":["Ζωγράφου"],"15772":["Αθήνα","Ζωγράφου","Ζωγράφος"],"15773":["Ζωγράφου","Αθήνα"],"16121":["Καισαριανή"],"16232":["Αθήνα"],"16371":["Αχαρνές"],"16451":["Αργυρούπολη"],"166 75":["Γλυφάδα"],"16673":["Αθήνα"],"16674":["Γλυφάδα"],"16675":["Γλυφάδα"],"17123":["Νέα Σμύρνη"],"17675":["Καλλιθέα"],"17676":["Καλλιθέα"],"18010":["Αίγινα"],"18233":["Άγιος Ιωάννης Ρέντη"],"18450":["Νίκαια"],"185 31":["Πειραιάς"],"185 32":["Πειραιάς"],"185 33":["Πειραιάς"],"185 34":["Πειραιάς"],"185 35":["Πειραιάς"],"185 36":["Πειραιάς"],"185 37":["Πειραιάς"],"185 38":["Πειραιάς"],"185 39":["Πειραιάς"],"185 41":["Πειραιάς"],"18532":["Πειραιάς"],"18533":["Πειραιάς"],"18541":["Πειραιάς"],"18758":["Κερατσίνι"],"18863":["Πέραμα"],"19004":["Σπάτα"],"19005":["Νέα Μάκρη"],"19016":["Αρτέμιδα"],"19400":["Κορωπί"],"20006":["Ζευγολατιό"],"21056":["Tolo","Τολό"],"21100":["Κάντια"],"22100":["Τρίπολη"],"23052":["Μολάοι"],"23100":["Σπάρτη"],"24100":["Καλαμάτα"],"250 06":["Akrata"],"25100":["Αίγιο","Βαλιμίτικα"],"25200":["Kato Achaia"],"26221":["Πάτρα"],"26331":["Πάτρα"],"26333":["Πάτρα"],"26504":["Ακταίο"],"27100":["Leventochori"],"27200":["Αμαλιάδα"],"29100":["Ζάκυνθος"],"30100":["Αγρίνιο"],"30132":["Αγρίνιο"],"31080":["Άγιος Νικήτας"],"31100":["Λευκάδα"],"34008":["Eretria"],"34100":["Χαλκίδα","Eretria","Φύλλα"],"35007":["Λιβανάτες Λοκρίδας"],"370 10":["Άφησσος"],"37005":["Στενή Βάλα"],"38221":["Βόλος"],"41002":["Λάρισα"],"41221":["Λάρισα"],"41222":["Λάρισα"],"41223":["Λάρισα","Λάριασ"],"41447":["Λάρισα"],"41500":["Λάρισα"],"42200":["Καστράκι"],"42222":["Λάρισα"],"43100":["Karditsa"],"44200":["Μετσόβου"],"45221":["Ιωάννινα"],"46 100":["Ηγουμενίτσα"],"48060":["Πάργα"],"49080":["Agios Georgios South","Lefkmmi Corfu"],"49084":["Σιναράδες"],"50200":["Πτολεμαΐδα"],"52100":["Καστοριά"],"54250":["Θεσσαλονίκη"],"54351":["Θεσσαλονίκη"],"54352":["Θεσσαλονίκη"],"54623":["Θεσσαλονίκη"],"54624":["Θεσσαλονίκη"],"54625":["Δήμος Θεσσαλονίκης"],"54626":["Θεσσαλονίκη","Thessaloniki"],"54645":["Θεσσαλονίκη"],"55131":["Καλαμαριά"],"55132":["Καλαμαριά","Θεσαλονίκη"],"55133":["Καλαμαριά","Θεσσαλονίκη"],"55134":["Καλαμαριά"],"56430":["Θεσσαλονίκη"],"56533":["Πολίχνη"],"56625":["Θεσσαλονίκη"],"59300":["Imathia"],"60005":["Πλαταμώνας"],"63100":["Kalives / Chalkidiki"],"64100":["Ακροβούνι"],"65201":["Καβάλα"],"65302":["Καβάλα"],"65403":["Καβάλα"],"66100":["Δράμα"],"67062":["Σταυρούπολη"],"68100":["Αλεξανδρούπολη"],"68200":["Ορεστιάδα"],"68300":["Διδυμότειχο"],"70002":["Zaros"],"70014":["Hersonissos"],"70400":["Zaros"],"71202":["Ηράκλειο"],"71306":["Ηράκλειο"],"73008":["Georgioupolis"],"73011":["Agia Roumeli"],"73014":["Maleme"],"73100":["Chania"],"73400":["Teloneio beach Kissamos"],"74052":["Rethymno"],"74056":["Αγία Γαλήνη"],"741 00":["Ρέθυμνο"],"7410":["Rethymno","Ρέθυμνο"],"74100":["Ρέθυμνο"],"74123":["Ρέθυμνο"],"83100":["Kokkari, Samos"],"84009":["Χώρα Ανάφης"],"84011":["Άνω Μεριά"],"84100":["Ερμούπολη","FINIKAS,SYROS","Ermoupoli Syros"],"84400":["Paros","Paroikia, Paros"],"84500":["Άνω Πιτροφός Άνδρου"],"84501":["Gavrio"],"84700":["Θήρα","Messaria","Firostefani"],"84701":["Santorini"],"84702":["Santorini"],"84703":["Σαντορινη"],"84800":["Τρυπητή","Προβατάς"],"85100":["Ρόδος"],"85101":["Ιαλυσός"],"85131":["Ρόδος"],"853 02":["Mastihari"],"85300":["Kos"],"85302":["Kos","Kardamena"]}